[
    {
        "domanda": "Cos'è l'UE in LTE?",
        "risposte": ["User Equipment", "Universal Encoder", "Unified Entity"],
        "corretta": 0,
        "categoria": "Reti"
    }
]
[
    {
        "domanda": "Qual è la funzione principale del protocollo TCP?",
        "risposte": ["Controllo della congestione", "Controllo degli errori", "Controllo della connessione"],
        "corretta": 0,
        "categoria": "Reti"
    },
    {
        "domanda": "Cosa significa NAT?",
        "risposte": ["Network Address Translation", "Network Access Translation", "Network Application Translation"],
        "corretta": 0,
        "categoria": "Reti"
    }
]
[
    {
        "domanda": "Qual è la differenza principale tra TCP e UDP?",
        "risposte": ["TCP è orientato alla connessione, UDP no", "UDP è più lento di TCP", "TCP non supporta il controllo degli errori"],
        "corretta": 0,
        "categoria": "Reti"
    },
    {
        "domanda": "Cosa rappresenta l'indirizzo IP?",